fickling/__init__.py
fickling/__main__.py
fickling/analysis.py
fickling/cli.py
fickling/context.py
fickling/exception.py
fickling/fickle.py
fickling/hook.py
fickling/import_hook.py
fickling/loader.py
fickling/ml.py
fickling/pickle.py
fickling/polyglot.py
fickling/pytorch.py
fickling/tracing.py
fickling-0.1.6.dist-info/METADATA
fickling-0.1.6.dist-info/WHEEL
fickling-0.1.6.dist-info/entry_points.txt
fickling-0.1.6.dist-info/licenses/LICENSE
fickling-0.1.6.dist-info/RECORD
